[
  {
    "id": "req-001",
    "programId": "prog-001",
    "coreSubjects": {
      "English": "C6",
      "Mathematics": "C6",
      "Social Studies": "C6",
      "Integrated Science": "C6"
    },
    "electiveSubjects": [
      {
        "subject": "Elective Mathematics",
        "min_grade": "B3"
      },
      {
        "subject": "Physics",
        "min_grade": "C6"
      },
      {
        "subject": "Any other elective",
        "min_grade": "C6"
      }
    ],
    "additionalRequirements": "Strong performance in mathematics required",
    "aggregatePoints": 24,
    "requirementComplexity": "basic",
    "programName": "B.Sc. Computer Science",
    "universityName": "University of Ghana"
  },
  {
    "id": "req-002",
    "programId": "prog-002",
    "coreSubjects": {
      "English": "C6",
      "Mathematics": "C6",
      "Social Studies": "C6",
      "Integrated Science": "C6"
    },
    "electiveSubjects": [
      {
        "subject": "Economics",
        "min_grade": "C6"
      },
      {
        "subject": "Government",
        "min_grade": "C6"
      },
      {
        "subject": "Any other elective",
        "min_grade": "C6"
      }
    ],
    "additionalRequirements": "Good performance in social sciences preferred",
    "aggregatePoints": 24,
    "requirementComplexity": "basic",
    "programName": "B.A. Economics",
    "universityName": "University of Ghana"
  },
  {
    "id": "req-003",
    "programId": "prog-003",
    "coreSubjects": {
      "English": "C6",
      "Mathematics": "C6",
      "Social Studies": "C6",
      "Integrated Science": "C6"
    },
    "electiveSubjects": [
      {
        "subject": "Elective Mathematics",
        "min_grade": "B3"
      },
      {
        "subject": "Physics",
        "min_grade": "B3"
      },
      {
        "subject": "Chemistry",
        "min_grade": "C6"
      }
    ],
    "additionalRequirements": "Must have strong mathematics and physics background",
    "aggregatePoints": 20,
    "requirementComplexity": "basic",
    "programName": "B.Sc. Civil Engineering",
    "universityName": "Kwame Nkrumah University of Science and Technology"
  },
  {
    "id": "req-004",
    "programId": "prog-004",
    "coreSubjects": {
      "English": "C6",
      "Mathematics": "C6",
      "Social Studies": "C6",
      "Integrated Science": "C6"
    },
    "electiveSubjects": [
      {
        "subject": "Elective Mathematics",
        "min_grade": "C6"
      },
      {
        "subject": "Any other 2 electives",
        "min_grade": "C6"
      }
    ],
    "additionalRequirements": "Teaching aptitude test required",
    "aggregatePoints": 24,
    "requirementComplexity": "basic",
    "programName": "B.Ed. Mathematics",
    "universityName": "University of Cape Coast"
  },
  {
    "id": "req-005",
    "programId": "prog-005",
    "coreSubjects": {
      "English": "B3",
      "Mathematics": "C6",
      "Social Studies": "C6",
      "Integrated Science": "C6"
    },
    "electiveSubjects": [
      {
        "subject": "Economics",
        "min_grade": "B3"
      },
      {
        "subject": "Any other 2 electives",
        "min_grade": "C6"
      }
    ],
    "additionalRequirements": "Interview and essay required for admission",
    "aggregatePoints": 18,
    "requirementComplexity": "basic",
    "programName": "B.Sc. Business Administration",
    "universityName": "Ashesi University"
  },
  {
    "id": "req-006",
    "programId": "prog-006",
    "coreSubjects": {
      "English": "C6",
      "Mathematics": "C6",
      "Social Studies": "C6",
      "Integrated Science": "C6"
    },
    "electiveSubjects": [
      {
        "subject": "Elective Mathematics",
        "min_grade": "B3"
      },
      {
        "subject": "Physics",
        "min_grade": "B3"
      },
      {
        "subject": "Chemistry",
        "min_grade": "C6"
      }
    ],
    "additionalRequirements": "Strong background in mathematics and physics required",
    "aggregatePoints": 20,
    "requirementComplexity": "basic",
    "programName": "B.Sc. Computer Engineering",
    "universityName": "Kwame Nkrumah University of Science and Technology"
  },
  {
    "id": "req-007",
    "programId": "prog-007",
    "coreSubjects": {
      "English": "C6",
      "Mathematics": "C6",
      "Social Studies": "C6",
      "Integrated Science": "C6"
    },
    "electiveSubjects": [
      {
        "subject": "Biology",
        "min_grade": "C6"
      },
      {
        "subject": "Chemistry",
        "min_grade": "C6"
      },
      {
        "subject": "Any other elective",
        "min_grade": "C6"
      }
    ],
    "additionalRequirements": "Medical fitness certificate and interview required",
    "aggregatePoints": 24,
    "requirementComplexity": "basic",
    "programName": "Diploma in Nursing",
    "universityName": "University of Cape Coast"
  },
  {
    "id": "req-008",
    "programId": "prog-008",
    "coreSubjects": {
      "English": "C6",
      "Mathematics": "C6",
      "Social Studies": "C6",
      "Integrated Science": "C6"
    },
    "electiveSubjects": [
      {
        "subject": "Biology",
        "min_grade": "C6"
      },
      {
        "subject": "Chemistry",
        "min_grade": "C6"
      },
      {
        "subject": "Any other elective",
        "min_grade": "C6"
      }
    ],
    "additionalRequirements": "Interest in sustainable agriculture practices",
    "aggregatePoints": 30,
    "requirementComplexity": "basic",
    "programName": "B.Sc. Agriculture",
    "universityName": "University for Development Studies"
  },
  {
    "id": "req-009",
    "programId": "prog-009",
    "coreSubjects": {
      "English": "C6",
      "Mathematics": "C6",
      "Social Studies": "C6",
      "Integrated Science": "C6"
    },
    "electiveSubjects": [
      {
        "subject": "Chemistry",
        "min_grade": "C6"
      },
      {
        "subject": "Any TWO from Physics/Mathematics/Biology/General Agriculture/Animal Husbandry/Crop Husbandry/Horticulture",
        "min_grade": "C6"
      }
    ],
    "additionalRequirements": "Must satisfy standard KNUST admission requirements",
    "aggregatePoints": 24,
    "requirementComplexity": "basic",
    "programName": "B.Sc. Agriculture",
    "universityName": "Kwame Nkrumah University of Science and Technology"
  },
  {
    "id": "req-010",
    "programId": "prog-010",
    "coreSubjects": {
      "English": "C6",
      "Mathematics": "C6",
      "Social Studies": "C6",
      "Integrated Science": "C6"
    },
    "electiveSubjects": [],
    "additionalRequirements": "Multiple admission tracks available - see detailed requirements",
    "aggregatePoints": 24,
    "admissionTracks": [
      {
        "name": "Science Track",
        "description": "For students with strong science background",
        "electiveOptions": [
          {
            "name": "Science Combination",
            "subjects": ["Chemistry", "Physics", "Biology"],
            "minGrades": {
              "Biology": "C6",
              "Physics": "C6",
              "Chemistry": "C6"
            },
            "additionalRules": []
          }
        ]
      },
      {
        "name": "Business Track",
        "description": "For students with business/economics background",
        "electiveOptions": [
          {
            "name": "Business Combination",
            "subjects": ["Economics", "Accounting", "Business Management"],
            "minGrades": {
              "Economics": "C6",
              "Accounting": "C6",
              "Business Management": "C6"
            },
            "additionalRules": ["Must have minimum B3 in Integrated Science for WASSCE applicants"]
          }
        ]
      },
      {
        "name": "General Arts Track",
        "description": "For students with arts/social science background",
        "electiveOptions": [
          {
            "name": "Arts Combination",
            "subjects": ["Economics", "Geography", "Elective Mathematics"],
            "minGrades": {
              "Economics": "C6",
              "Geography": "C6",
              "Elective Mathematics": "C6"
            },
            "additionalRules": ["Must have minimum B3 in Integrated Science for WASSCE applicants"]
          }
        ]
      },
      {
        "name": "General Agriculture Track",
        "description": "For students with agricultural background",
        "electiveOptions": [
          {
            "name": "Agriculture Combination",
            "subjects": ["Chemistry", "Physics", "General Agriculture"],
            "minGrades": {
              "Physics": "C6",
              "Chemistry": "C6",
              "General Agriculture": "C6"
            },
            "additionalRules": []
          }
        ]
      }
    ],
    "requirementComplexity": "advanced",
    "programName": "B.Sc. Agribusiness Management",
    "universityName": "Kwame Nkrumah University of Science and Technology"
  }
]